shahin/__init__.py
shahin/api.py
shahin/asynco.py
shahin/button.py
shahin/config.py
shahin/context.py
shahin/decorators.py
shahin/exceptions.py
shahin/filters.py
shahin/helpers.py
shahin/jobs.py
shahin/keyboards.py
shahin/keypad.py
shahin/logger.py
shahin/metadata.py
shahin/rubino.py
shahin/tv.py
shahin/update.py
shahin/utils.py
shahin/adaptorrubka/__init__.py
shahin/adaptorrubka/enums.py
shahin/adaptorrubka/exceptions.py
shahin/adaptorrubka/client/__init__.py
shahin/adaptorrubka/client/client.py
shahin/adaptorrubka/crypto/__init__.py
shahin/adaptorrubka/crypto/crypto.py
shahin/adaptorrubka/methods/__init__.py
shahin/adaptorrubka/methods/methods.py
shahin/adaptorrubka/network/__init__.py
shahin/adaptorrubka/network/helper.py
shahin/adaptorrubka/network/network.py
shahin/adaptorrubka/network/socket.py
shahin/adaptorrubka/sessions/__init__.py
shahin/adaptorrubka/sessions/sessions.py
shahin/adaptorrubka/types/__init__.py
shahin/adaptorrubka/types/socket/__init__.py
shahin/adaptorrubka/types/socket/message.py
shahin/adaptorrubka/utils/__init__.py
shahin/adaptorrubka/utils/configs.py
shahin/adaptorrubka/utils/utils.py
shahinlibrary-1.0.2.dist-info/METADATA
shahinlibrary-1.0.2.dist-info/WHEEL
shahinlibrary-1.0.2.dist-info/entry_points.txt
shahinlibrary-1.0.2.dist-info/top_level.txt
shahinlibrary-1.0.2.dist-info/RECORD
