Metadata-Version: 2.4
Name: shahinlibrary
Version: 1.0.2
Summary: Rubika: A Python library for interacting with the Rubika Bot API. This library provides an easy-to-use interface to send messages, polls, stickers, media files, manage groups and channels, handle inline keyboards, and implement advanced bot features like subscription management, user authentication, and message handling. Ideal for developers looking to automate and extend their Rubika bots with Python.
Author: shahin
Author-email: mahdiahmadi.1208@gmail.com
Maintainer: Shahin
License: MIT
Classifier: Development Status :: 5 - Production/Stable
Classifier: Intended Audience :: Developers
Classifier: Programming Language :: Python :: 3
Classifier: Programming Language :: Python :: 3.8
Classifier: Programming Language :: Python :: 3.9
Classifier: Programming Language :: Python :: 3.10
Classifier: License :: OSI Approved :: MIT License
Classifier: Operating System :: OS Independent
Classifier: Topic :: Communications :: Chat
Classifier: Topic :: Software Development :: Libraries
Classifier: Natural Language :: Persian
Requires-Python: >=3.6
Requires-Dist: requests
Requires-Dist: websocket-client
Requires-Dist: pycryptodome
Requires-Dist: aiohttp
Requires-Dist: httpx
Requires-Dist: tqdm
Requires-Dist: mutagen
Requires-Dist: markdownify
Requires-Dist: filetype
Requires-Dist: aiofiles
Dynamic: author
Dynamic: author-email
Dynamic: classifier
Dynamic: description
Dynamic: description-content-type
Dynamic: license
Dynamic: maintainer
Dynamic: requires-dist
Dynamic: requires-python
Dynamic: summary
